<?xml version="1.0" encoding="windows-1251" ?>
<string_table>

	<string id="radiation_outfit_3_name">
		<text>«Amanecer» camuflaje de bosque</text>
	</string>
	
	<string id="dolg_radiation_outfit_1_name">
		<text>Naranja «Amanecer» (Deber)</text>
	</string>
	
	<string id="dolg_radiation_outfit_2_name">
		<text>«Amanecer» camuflaje de bosque (Deber)</text>
	</string>
	
	<string id="dolg_radiation_outfit_3_name">
		<text>«Amanecer» camuflaje urbano (Deber)</text>
	</string>
	
	<string id="heavy_outfit_2_name">
		<text>Un traje blindado pesado con una descarga</text>
	</string>
	<string id="heavy_outfit_2_descr">
		<text>El traje de armadura pesada tiene un aspecto similar al de un exoesqueleto, pero la primera y principal diferencia que llama la atencion es la ausencia de casco y de servos en los brazos y las piernas, asi como de una bateria en la espalda. Debido a esta diferencia, un traje blindado pesado es mas ligero que un exoesqueleto y tambien permite a su portador correr. A pesar de su popularidad, el traje nunca recibio su nombre. \N - %c[0,170,170,170]CARACTERISTICAS:\N-[0,153,255,255] - %c[0,140,140,140] armadura pesada \N-[0,170,170,170]Clase de armadura: \N - %c[0,93,0,116] - %c[0,140,140,140] Cabeza: %c[0,170,170,170]none\n%c[0,93,0,116] - %c[0,140,140] Ojos: %c[0,170,170,170]absent\n%c[0,93,0,116] - %c[0,140,140,140] Menton: %c[0,170,170,170]absent\n%c[0,93,0,116] - %c[0,140,140,140] Cuello: %c[0,170,170,170]absent\n%c[0,93,0,116] - %c[0,140,140,140] Torso: %c[0,170,170,170]V\n%c[0,93,0,116] - %c[0,140,140,140] Hombros: %c[0,170,170,170]V\n%c[0,93,0,116] - %c[0,140,140,140] Pinceles: %c[0,170,170,170]IV\n%c[0,93,0,116] - %c[0,140,140,140] Brazos: %c[0,170,170,IV\n%c[0,93,0,116] - %c[0,140,140,140] Caderas: %c[0,170,170,170]V\n%c[0,93,0,116] - %c[0,140,140] Rodillas y espinillas: %c[0,170,170]V\n%c[0,93,0,116] - %c[0,140,140] Pies: %c[0,170,170,170]V\n%c[0,170,170,170]PIES:\n%c[0,100,0,15] - %c[0,140,140,140] capacidad de carga aumentada</text>
	</string>
	
	<string id="heavy_outfit_3_name">
		<text>Una armadura pesada de pantano</text>
	</string>
	
	<string id="heavy_outfit_dolg_1_name">
		<text>Traje blindado pesado de camuflaje forestal (Deber)</text>
	</string>
	
	<string id="heavy_outfit_dolg_2_name">
		<text>Traje blindado pesado de camuflaje urbano (Deber)</text>
	</string>
	
	<string id="heavy_outfit_dolg_3_name">
		<text>Traje de armadura pesada oscura (Deber)</text>
	</string>
	
	<string id="heavy_outfit_dolg_4_name">
		<text>Armadura pesada naranja (Deber)</text>
	</string>
	
	<string id="heavy_outfit_dolg_5_name">
		<text>Traje de armadura pesada alternativo (Deber)</text>
	</string>
	
	<string id="bandit_radiation_outfit_1_name">
		<text>Incursion «Amanecer»</text>
	</string>
	
	<string id="bandit_radiation_outfit_2_name">
		<text>"Amanecer" de Bandit con descarga</text>
	</string>
	<string id="bandit_radiation_outfit_2_descr">
		<text>El traje de armadura pesada se parece a un exoesqueleto en apariencia, pero la primera y principal diferencia que llama la atencion es la ausencia de servos en los brazos y las piernas, asi como un paquete de baterias detras de la espalda. Es miembro de la banda del Sultan. Creo el traje de armadura pesada para reemplazar los costosos exoesqueletos, debido a esta diferencia, el traje de armadura pesada es mas ligero que el exoesqueleto y permite al usuario correr. En todos los demas aspectos, un traje blindado es identico a un exoesqueleto, salvo que tiene una proteccion ligeramente menor contra las balas y las rafagas de metralla y proporciona al usuario una menor proteccion contra los impactos. A pesar de su popularidad, el traje nunca recibio su nombre. \N - %c[0,170,170,170]CARACTERISTICAS:\N-[0,153,255,255] - %c[0,140,140,140] armadura muy pesada \N-[0,170,170,170]CLASE DE PROTECCION DE LA ARMADURA: \N - %c[0,93,0,116] - %c[0,140,140,140] Cabeza: %c[0,170,170,170]\N - %c[0,93,0,116] - %c[0,140,140] Ojos: %c[0,170,170,170]IV\n%c[0,93,0,116] - %c[0,140,140,140] Barbilla: %c[0,170,170,IV\n%c[0,93,0,116] - %c[0,140,140,140] Cuello: %c[0,170,170,170]IV\n%c[0,93,0,116] - %c[0,140,140,140] Torso: %c[0,170,170,170]V\n%c[0,93,0,116] - %c[0,140,140] Hombros: %c[0,170,170,170]V\n%c[0,93,0,116] - %c[0,140,140,140] Munecas: %c[0,170,170,170]IV\n%c[0,93,0,116] - %c[0,140,140,140] Brazos: %c[0,170,170,170]IV\n%c[0,93,0,116] - %c[0,140,140,140] Caderas: %c[0,170,170,170]V\n%c[0,93,0,116] - %c[0,140,140,140] Rodillas y espinillas: %c[0,170,170,170]V\n%c[0,93,0,116] - %c[0,140,140,140] Pies: %c[0,170,170,170]V\n%c[0,170,170,170]PIES:\n%c[0,100,0,15] - %c[0,140,140,140] mayor capacidad de carga en comparacion con la convencional,170,170,170]V\n%c[0,93,0,116] • %c[0,140,140,140] Ступни: %c[0,170,170,170]V\n \n%c[0,170,170,170]ОСОБЕННОСТЬ:\n%c[0,100,0,15] • %c[0,140,140,140] повышена грузоподъёмность по сравнению с обычным</text>
	</string>
	
	<string id="bandit_heavy_outfit_1_name">
		<text>Traje de armadura pesada de los Raiders</text>
	</string>
	
	<string id="bandit_heavy_outfit_2_name">
		<text>Traje de armadura pesada de gangster con descarga</text>
	</string>
	<string id="bandit_heavy_outfit_2_descr">
		<text>El traje de armadura pesada tiene un aspecto similar al de un exoesqueleto, pero la primera y principal diferencia que llama la atencion es la ausencia de casco y de servos en los brazos y las piernas, asi como de una bateria en la espalda. Debido a esta diferencia, un traje blindado pesado es mas ligero que un exoesqueleto y tambien permite a su portador correr. A pesar de su popularidad, el traje nunca recibio su nombre. \N - %c[0,170,170,170]CARACTERISTICAS:\N-[0,153,255,255] - %c[0,140,140,140] armadura pesada \N-[0,170,170,170]Clase de armadura: \N - %c[0,93,0,116] - %c[0,140,140,140] Cabeza: %c[0,170,170,170]none\n%c[0,93,0,116] - %c[0,140,140] Ojos: %c[0,170,170,170]absent\n%c[0,93,0,116] - %c[0,140,140,140] Menton: %c[0,170,170,170]absent\n%c[0,93,0,116] - %c[0,140,140,140] Cuello: %c[0,170,170,170]absent\n%c[0,93,0,116] - %c[0,140,140,140] Torso: %c[0,170,170,170]V\n%c[0,93,0,116] - %c[0,140,140,140] Hombros: %c[0,170,170,170]V\n%c[0,93,0,116] - %c[0,140,140,140] Pinceles: %c[0,170,170,170]IV\n%c[0,93,0,116] - %c[0,140,140,140] Brazos: %c[0,170,170,IV\n%c[0,93,0,116] - %c[0,140,140,140] Caderas: %c[0,170,170,170]V\n%c[0,93,0,116] - %c[0,140,140] Rodillas y espinillas: %c[0,170,170]V\n%c[0,93,0,116] - %c[0,140,140] Pies: %c[0,170,170,170]V\n%c[0,170,170,170]CARACTERISTICAS:\n%c[0,100,0,15] - %c[0,140,140,140] mayor capacidad de carga en comparacion con la convencional</text>
	</string>
	
	<string id="freedom_heavy_outfit_1_name">
		<text>Traje blindado pesado de camuflaje de pantano (Libertad)</text>
	</string>
	
	<string id="freedom_heavy_outfit_2_name">
		<text>Traje blindado pesado de camuflaje forestal (Libertad)</text>
	</string>
	
	<string id="freedom_heavy_outfit_3_name">
		<text>Traje blindado pesado con descarga (Libertad)</text>
	</string>
	<string id="freedom_heavy_outfit_3_desc">
		<text>El traje de armadura pesada tiene un aspecto similar al de un exoesqueleto, pero la primera y principal diferencia que llama la atencion es la ausencia de casco y de servos en los brazos y las piernas, asi como de una bateria en la espalda. Debido a esta diferencia, un traje blindado pesado es mas ligero que un exoesqueleto y tambien permite a su portador correr. A pesar de su popularidad, el traje nunca recibio su nombre. \N - %c[0,170,170,170]CARACTERISTICAS:\N-[0,153,255,255] - %c[0,140,140,140] armadura pesada \N-[0,170,170,170]Clase de armadura: \N - %c[0,93,0,116] - %c[0,140,140,140] Cabeza: %c[0,170,170,170]none\n%c[0,93,0,116] - %c[0,140,140] Ojos: %c[0,170,170,170]absent\n%c[0,93,0,116] - %c[0,140,140,140] Menton: %c[0,170,170,170]absent\n%c[0,93,0,116] - %c[0,140,140,140] Cuello: %c[0,170,170,170]absent\n%c[0,93,0,116] - %c[0,140,140,140] Torso: %c[0,170,170,170]V\n%c[0,93,0,116] - %c[0,140,140,140] Hombros: %c[0,170,170,170]V\n%c[0,93,0,116] - %c[0,140,140,140] Pinceles: %c[0,170,170,170]IV\n%c[0,93,0,116] - %c[0,140,140,140] Brazos: %c[0,170,170,IV\n%c[0,93,0,116] - %c[0,140,140,140] Caderas: %c[0,170,170,170]V\n%c[0,93,0,116] - %c[0,140,140] Rodillas y espinillas: %c[0,170,170]V\n%c[0,93,0,116] - %c[0,140,140] Pies: %c[0,170,170,170]V\n%c[0,170,170,170]PIES:\n%c[0,100,0,15] - %c[0,140,140,140] capacidad de carga aumentada</text>
	</string>
	
	<string id="freedom_radiation_outfit_1_name">
		<text>«Amanecer» (Libertad)</text>
	</string>
	
	<string id="freedom_radiation_outfit_2_name">
		<text>Camuflado «Amanecer» (Libertad)</text>
	</string>
	
	<string id="freedom_radiation_outfit_3_name">
		<text>"Amanecer" con descarga (Libertad)</text>
	</string>
	<string id="freedom_radiation_outfit_3_descr">
		<text>El traje de armadura pesada se parece a un exoesqueleto en apariencia, pero la primera y principal diferencia que llama la atencion es la ausencia de servos en los brazos y las piernas, asi como un paquete de baterias detras de la espalda. Fabricado por artesanos del mercado negro a peticion de la Libertad, para sustituir a los caros exoesqueletos, debido a esta diferencia, el traje de armadura pesada es mas ligero que el exoesqueleto, y ademas permite a su propietario correr. En todos los demas aspectos, un traje blindado es identico a un exoesqueleto, salvo que tiene una proteccion ligeramente menor contra las balas y las rafagas de metralla y proporciona al usuario una menor proteccion contra los impactos. A pesar de su popularidad, el traje nunca recibio su nombre. \n \n%c[0,170,170,170]CARACTERISTICAS:\n%c[0,153,255,255] - %c[0,140,140,140] armadura muy pesada \n \n%c[0,170,170,170]CLASE DE PROTECCION DE LA ARMADURA:\n%c[0,93,0,116] - %c[0,140,140,140] Cabeza: %c[0,170,170,170]IV\n%c[0,93,0,116] - %c[0,140,140,140] Ojos: %c[0,170,170,IV\n%c[0,93,0,116] - %c[0,140,140,140] Barbilla: %c[0,170,170,170]IV\n%c[0,93,0,116] - %c[0,140,140,140] Cuello: %c[0,170,170,IV\n%c[0,93,0,116] - %c[0,140,140,140] Torso: %c[0,170,170,170]V\n%c[0,93,0,116] - %c[0,140,140,140] Hombros: %c[0,170,170,170]V\n%c[0,93,0,116] - %c[0,140,140,140] Pinceles: %c[0,170,170,170]IV\n%c[0,93,0,116] - %c[0,140,140,140] Brazos: %c[0,170,170,IV\n%c[0,93,0,116] - %c[0,140,140,140] Caderas: %c[0,170,170,170]V\n%c[0,93,0,116] - %c[0,140,140] Rodillas y espinillas: %c[0,170,170]V\n%c[0,93,0,116] - %c[0,140,140] Pies: %c[0,170,170,170]V\n%c[0,170,170,170]PIES:\n%c[0,100,0,15] - %c[0,140,140,140] capacidad de carga aumentada</text>
	</string>
	
	<string id="radiation_outfit_4_name">
		<text>"Amanecer" con descarga</text>
	</string>
	<string id="radiation_outfit_4_descr">
		<text>El traje de armadura pesada tiene un aspecto similar al de un exoesqueleto, pero la primera y principal diferencia que llama la atencion es la ausencia de servos en los brazos y las piernas, asi como de una bateria en la espalda. Debido a esta diferencia, el traje blindado pesado es mas ligero que el exoesqueleto y tambien permite a su portador correr. En todos los demas aspectos, el traje blindado es identico al exoesqueleto, salvo que tiene una proteccion ligeramente menor contra las balas y las rafagas de metralla y proporciona al usuario una menor proteccion contra los impactos. A pesar de su popularidad, el traje nunca recibio su nombre. \N - %c[0,170,170,170]CARACTERISTICAS:\N-[0,153,255,255] - %c[0,140,140,140] armadura muy pesada \N-[0,170,170,170]CLASE DE PROTECCION DE LA ARMADURA: \N - %c[0,93,0,116] - %c[0,140,140,140] Cabeza: %c[0,170,170,170]\N - %c[0,93,0,116] - %c[0,140,140] Ojos: %c[0,170,170,170]IV\n%c[0,93,0,116] - %c[0,140,140,140] Barbilla: %c[0,170,170,IV\n%c[0,93,0,116] - %c[0,140,140,140] Cuello: %c[0,170,170,170]IV\n%c[0,93,0,116] - %c[0,140,140,140] Torso: %c[0,170,170,170]V\n%c[0,93,0,116] - %c[0,140,140] Hombros: %c[0,170,170,170]V\n%c[0,93,0,116] - %c[0,140,140,140] Munecas: %c[0,170,170,170]IV\n%c[0,93,0,116] - %c[0,140,140,140] Brazos: %c[0,170,170,170]IV\n%c[0,93,0,116] - %c[0,140,140,140] Caderas: %c[0,170,170,170]V\n%c[0,93,0,116] - %c[0,140,140,140] Rodillas y espinillas: %c[0,170,170,170]V\n%c[0,93,0,116] - %c[0,140,140,140] Pies: %c[0,170,170,170]V\n%c[0,170,170,170]PIES:\n%c[0,100,0,15] - %c[0,140,140,140] mayor resistencia al desgaste y capacidad de carga</text>
	</string>
	
	<string id="merc_heavy_outfit_1_name">
		<text>Traje blindado pesado de camuflaje urbano (Mercenarios)</text>
	</string>
	
	<string id="merc_heavy_outfit_2_name">
		<text>Traje blindado pesado de camuflaje naval (Mercenarios)</text>
	</string>
	
	<string id="merc_heavy_outfit_3_name">
		<text>Traje blindado pesado de camuflaje (Mercenarios)</text>
	</string>
	
	<string id="merc_radiation_outfit_1_name">
		<text>"Amanecer" en camuflaje naval (Mercenarios)</text>
	</string>
	
	<string id="merc_radiation_outfit_2_name">
		<text>«Amanecer» en camuflaje urbano (Mercenarios)</text>
	</string>
	
	<string id="merc_radiation_outfit_3_name">
		<text>Camuflaje «Amanecer» (Mercenarios)</text>
	</string>
	
	<string id="Trajelith_heavy_outfit_1_name">
		<text>Traje de armadura pesada oscura (Trajelito)</text>
	</string>
	
	<string id="Trajelith_heavy_outfit_2_name">
		<text>Traje de armadura pesada marron (Trajelito)</text>
	</string>
	
	<string id="Trajelith_radiation_outfit_1_name">
		<text>Marron «Amanecer» (Trajelito)</text>
	</string>
	
	<string id="Trajelith_radiation_outfit_2_name">
		<text>Oscuro «Amanecer» (Trajelito)</text>
	</string>
	
	<string id="csky_heavy_outfit_1_name">
		<text>Traje de armadura pesada reforzada (Cielo despejado)</text>
	</string>
	<string id="csky_heavy_outfit_1_descr">
		<text>El traje de armadura pesada tiene un aspecto similar al de un exoesqueleto, pero la primera y principal diferencia que llama la atencion es la ausencia de casco y de servos en los brazos y las piernas, asi como de una bateria en la espalda. Debido a esta diferencia, un traje blindado pesado es mas ligero que un exoesqueleto y tambien permite a su portador correr. A pesar de su popularidad, el traje nunca recibio su nombre. \N - %c[0,170,170,170]CARACTERISTICAS:\N-[0,153,255,255] - %c[0,140,140,140] armadura pesada \N-[0,170,170,170]Clase de armadura: \N - %c[0,93,0,116] - %c[0,140,140,140] Cabeza: %c[0,170,170,170]none\n%c[0,93,0,116] - %c[0,140,140] Ojos: %c[0,170,170,170]absent\n%c[0,93,0,116] - %c[0,140,140,140] Menton: %c[0,170,170,170]absent\n%c[0,93,0,116] - %c[0,140,140,140] Cuello: %c[0,170,170,170]absent\n%c[0,93,0,116] - %c[0,140,140,140] Torso: %c[0,170,170,170]V\n%c[0,93,0,116] - %c[0,140,140,140] Hombros: %c[0,170,170,170]V\n%c[0,93,0,116] - %c[0,140,140,140] Pinceles: %c[0,170,170,170]IV\n%c[0,93,0,116] - %c[0,140,140,140] Brazos: %c[0,170,170,IV\n%c[0,93,0,116] - %c[0,140,140,140] Caderas: %c[0,170,170,170]V\n%c[0,93,0,116] - %c[0,140,140] Rodillas y espinillas: %c[0,170,170]V\n%c[0,93,0,116] - %c[0,140,140] Pies: %c[0,170,170,170]V\n%c[0,170,170,170]CARACTERISTICAS:\n%c[0,100,0,15] - %c[0,140,140,140,140]\n%c[0,140,140]\n%c[0,140,140,140]\n%c[0,140,140,140] resistencia mejorada a las balas,\n%c[0,170,170,170]\n%c[0,100,0,15]</text>
	</string>
	
	<string id="csky_radiation_outfit_1_name">
		<text>Reforzado «Amanecer» (Cielo despejado)</text>
	</string>
	<string id="csky_radiation_outfit_1_descr">
		<text>El traje de armadura pesada se parece a un exoesqueleto en apariencia, pero la primera y principal diferencia que llama la atencion es la ausencia de servos en los brazos y las piernas, asi como de una bateria detras de la espalda. El fabricante de tecnologia Novikov, hecho para reemplazar los costosos exoesqueletos, debido a esta diferencia, el traje blindado pesado es mas ligero que el exoesqueleto, y tambien permite a su dueno correr. En todos los demas aspectos, un traje blindado es identico a un exoesqueleto, salvo que tiene algo menos de proteccion contra las balas y las rafagas de metralla y proporciona al usuario menos proteccion contra los impactos. A pesar de su popularidad, el traje nunca recibio su nombre. \N - %c[0,170,170,170]CARACTERISTICAS:\N-[0,153,255,255] - %c[0,140,140,140] armadura muy pesada \N-[0,170,170,170]CLASE DE PROTECCION DE LA ARMADURA: \N - %c[0,93,0,116] - %c[0,140,140,140] Cabeza: %c[0,170,170,170]\N - %c[0,93,0,116] - %c[0,140,140] Ojos: %c[0,170,170,170]IV\n%c[0,93,0,116] - %c[0,140,140,140] Barbilla: %c[0,170,170,IV\n%c[0,93,0,116] - %c[0,140,140,140] Cuello: %c[0,170,170,170]IV\n%c[0,93,0,116] - %c[0,140,140,140] Torso: %c[0,170,170,170]V\n%c[0,93,0,116] - %c[0,140,140] Hombros: %c[0,170,170,170]V\n%c[0,93,0,116] - %c[0,140,140,140] Munecas: %c[0,170,170,170]V\n%c[0,93,0,116] - %c[0,140,140] Brazos: %c[0,170,170,170]V\n%c[0,93,0,116] - %c[0,140,140] Caderas: %c[0,170,170,170]V\n%c[0,93,0,116] - %c[0,140,140] Rodillas y espinillas: %c[0,170,170]V\n%c[0,93,0,116] - %c[0,140,140] Pies: %c[0,170,170,170]V\n%c[0,170,170,170]CARACTERISTICAS:\n%c[0,100,0,15] - %c[0,140,140,140,140] aumento del numero de accesorios para modulos adicionales; mayor resistencia a las balas, proteccion contra desgarros y explosiones</text>
	</string>
	
	<string id="csky_novice_outfit_2_name">
		<text>Chaqueta Clear Skies</text>
	</string>
	
	<string id="heavy_outfit_name">
		<text>Armadura pesada</text>
	</string>
	<string id="heavy_outfit_description">
		<text>El traje de armadura pesada tiene un aspecto similar al de un exoesqueleto, pero la primera y principal diferencia que llama la atencion es la ausencia de casco y de servos en los brazos y las piernas, asi como de una bateria en la espalda. Debido a esta diferencia, un traje blindado pesado es mas ligero que un exoesqueleto y tambien permite a su portador correr. A pesar de su popularidad, el traje nunca recibio su nombre. \N - %c[0,170,170,170]CARACTERISTICAS:\N-[0,153,255,255] - %c[0,140,140,140] armadura pesada \N-[0,170,170,170]CLASE DE PROTECCION DE LA ARMADURA:\N-[0,93,0,116] - %c[0,140,140,140,140] Cabeza: %c[0,170,170,170]ausente\n%c[0,93,0,116] - %c[0,140,140,140] Ojos: %c[0,170,170,170]ausente\n%c[0,93,0,116] - %c[0,140,140,140] Menton: %c[0,170,170,170]ausente\n%c[0,93,0,116] - %c[0,140,140,140] Cuello: %c[0,170,170,170]absent\n%c[0,93,0,116] - %c[0,140,140,140] Torso: %c[0,170,170,170]V\n%c[0,93,0,116] - %c[0,140,140] Hombros: %c[0,170,170,170]V\n%c[0,93,0,116] - %c[0,140,140,140] Munecas: %c[0,170,170,170]IV\n%c[0,93,0,116] - %c[0,140,140,140] Brazos: %c[0,170,170,170]IV\n%c[0,93,0,116] - %c[0,140,140,140] Caderas: %c[0,170,170,170]V\n%c[0,93,0,116] - %c[0,140,140,140] Rodillas y espinillas: %c[0,170,170,170]V\n%c[0,93,0,116] - %c[0,140,140,140] Pies: %c[0,170,170]V</text>
	</string>
	
	<string id="heavy_outfit_1_name">
		<text>Un traje blindado pesado con una descarga</text>
	</string>
	<string id="heavy_outfit_1_description">
		<text>El traje de armadura pesada tiene un aspecto similar al de un exoesqueleto, pero la primera y principal diferencia que llama la atencion es la ausencia de casco y de servos en los brazos y las piernas, asi como de una bateria en la espalda. Debido a esta diferencia, un traje blindado pesado es mas ligero que un exoesqueleto y tambien permite a su portador correr. A pesar de su popularidad, el traje nunca recibio su nombre. \N - %c[0,170,170,170]CARACTERISTICAS:\N-[0,153,255,255] - %c[0,140,140,140] armadura pesada \N-[0,170,170,170]Clase de armadura: \N - %c[0,93,0,116] - %c[0,140,140,140] Cabeza: %c[0,170,170,170]none\n%c[0,93,0,116] - %c[0,140,140] Ojos: %c[0,170,170,170]absent\n%c[0,93,0,116] - %c[0,140,140,140] Menton: %c[0,170,170,170]absent\n%c[0,93,0,116] - %c[0,140,140,140] Cuello: %c[0,170,170,170]absent\n%c[0,93,0,116] - %c[0,140,140,140] Torso: %c[0,170,170,170]V\n%c[0,93,0,116] - %c[0,140,140,140] Hombros: %c[0,170,170,170]V\n%c[0,93,0,116] - %c[0,140,140,140] Pinceles: %c[0,170,170,170]IV\n%c[0,93,0,116] - %c[0,140,140,140] Brazos: %c[0,170,170,IV\n%c[0,93,0,116] - %c[0,140,140,140] Caderas: %c[0,170,170,170]V\n%c[0,93,0,116] - %c[0,140,140] Rodillas y espinillas: %c[0,170,170]V\n%c[0,93,0,116] - %c[0,140,140] Pies: %c[0,170,170,170]V\n%c[0,170,170,170]PIES:\n%c[0,100,0,15] - %c[0,140,140,140] capacidad de carga aumentada</text>
	</string>
	
	<string id="dolg_heavy_outfit_name">
		<text>Traje blindado pesado PSZ-9d</text>
	</string>
	<string id="dolg_heavy_outfit_description">
		<text>Un primer modelo del traje de Debera es el traje blindado de las fuerzas especiales de la serie PS3-9, adaptado para su uso en la Zona. Externamente, el traje de armadura pesada se asemeja a un exoesqueleto, pero la primera y principal diferencia que llama la atencion es la ausencia de casco y de servos en los brazos y las piernas, asi como de una bateria en la espalda. Debido a esta diferencia, un traje blindado pesado es mas ligero que un exoesqueleto y tambien permite a su portador correr. A pesar de su popularidad, el traje nunca recibio su nombre. \N - %c[0,170,170,170]CARACTERISTICAS:\N-[0,153,255,255] - %c[0,140,140,140] armadura pesada \N-[0,170,170,170]Clase de armadura: \N - %c[0,93,0,116] - %c[0,140,140,140] Cabeza: %c[0,170,170,170]none\n%c[0,93,0,116] - %c[0,140,140] Ojos: %c[0,170,170,170]absent\n%c[0,93,0,116] - %c[0,140,140,140] Menton: %c[0,170,170,170]absent\n%c[0,93,0,116] - %c[0,140,140,140] Cuello: %c[0,170,170,170]absent\n%c[0,93,0,116] - %c[0,140,140,140] Torso: %c[0,170,170,170]V\n%c[0,93,0,116] - %c[0,140,140,140] Hombros: %c[0,170,170,170]V\n%c[0,93,0,116] - %c[0,140,140,140] Pinceles: %c[0,170,170,170]IV\n%c[0,93,0,116] - %c[0,140,140,140] Brazos: %c[0,170,170,IV\n%c[0,93,0,116] - %c[0,140,140,140] Caderas: %c[0,170,170,170]V\n%c[0,93,0,116] - %c[0,140,140] Rodillas y espinillas: %c[0,170,170]V\n%c[0,93,0,116] - %c[0,140,140] Pies: %c[0,170,170,170]V\n%c[0,170,170,170]PIES:\n%c[0,100,0,15] - %c[0,140,140,140,140] aumento del parametro "Proteccion de lagrimas"</text>
	</string>
	
	<string id="Trajelith_heavy_outfit_name">
		<text>Armadura pesada (Trajelito)</text>
	</string>
	<string id="Trajelith_heavy_outfit_description">
		<text>El traje de armadura pesada tiene un aspecto similar al de un exoesqueleto, pero la primera y principal diferencia que llama la atencion es la ausencia de casco y de servos en los brazos y las piernas, asi como de una bateria en la espalda. Debido a esta diferencia, un traje blindado pesado es mas ligero que un exoesqueleto y tambien permite a su portador correr. A pesar de su popularidad, el traje nunca recibio su nombre. \N - %c[0,170,170,170]CARACTERISTICAS:\N-[0,153,255,255] - %c[0,140,140,140] armadura pesada \N-[0,170,170,170]Clase de armadura: \N - %c[0,93,0,116] - %c[0,140,140,140] Cabeza: %c[0,170,170,170]none\n%c[0,93,0,116] - %c[0,140,140] Ojos: %c[0,170,170,170]absent\n%c[0,93,0,116] - %c[0,140,140,140] Menton: %c[0,170,170,170]absent\n%c[0,93,0,116] - %c[0,140,140,140] Cuello: %c[0,170,170,170]absent\n%c[0,93,0,116] - %c[0,140,140,140] Torso: %c[0,170,170,170]V\n%c[0,93,0,116] - %c[0,140,140,140] Hombros: %c[0,170,170,170]V\n%c[0,93,0,116] - %c[0,140,140,140] Pinceles: %c[0,170,170,170]IV\n%c[0,93,0,116] - %c[0,140,140,140] Brazos: %c[0,170,170,IV\n%c[0,93,0,116] - %c[0,140,140,140] Caderas: %c[0,170,170,170]V\n%c[0,93,0,116] - %c[0,140,140,140] Rodillas y espinillas: %c[0,170,170]V\n%c[0,93,0,116] - %c[0,140,140,140] Pies: %c[0,170,170,170]V\n%c[0,170,170,170]PIES:\n%c[0,100,0,15] - %c[0,140,140,140] mejorados</text>
	</string>
	
	<string id="freedom_heavy_outfit_name">
		<text>Armadura pesada (Libertad)</text>
	</string>
	<string id="freedom_heavy_outfit_description">
		<text>El traje de armadura pesada tiene un aspecto similar al de un exoesqueleto, pero la primera y principal diferencia que llama la atencion es la ausencia de casco y de servos en los brazos y las piernas, asi como de una bateria en la espalda. Debido a esta diferencia, un traje blindado pesado es mas ligero que un exoesqueleto y tambien permite a su portador correr. A pesar de su popularidad, el traje nunca recibio su nombre. \N - %c[0,170,170,170]CARACTERISTICAS:\N-[0,153,255,255] - %c[0,140,140,140] armadura pesada \N-[0,170,170,170]CLASE DE PROTECCION DE LA ARMADURA:\N-[0,93,0,116] - %c[0,140,140,140,140] Cabeza: %c[0,170,170,170]ausente\n%c[0,93,0,116] - %c[0,140,140,140] Ojos: %c[0,170,170,170]ausente\n%c[0,93,0,116] - %c[0,140,140,140] Menton: %c[0,170,170,170]ausente\n%c[0,93,0,116] - %c[0,140,140,140] Cuello: %c[0,170,170,170]absent\n%c[0,93,0,116] - %c[0,140,140,140] Torso: %c[0,170,170,170]V\n%c[0,93,0,116] - %c[0,140,140] Hombros: %c[0,170,170,170]V\n%c[0,93,0,116] - %c[0,140,140,140] Munecas: %c[0,170,170,170]IV\n%c[0,93,0,116] - %c[0,140,140,140] Brazos: %c[0,170,170,170]IV\n%c[0,93,0,116] - %c[0,140,140,140] Caderas: %c[0,170,170,170]V\n%c[0,93,0,116] - %c[0,140,140,140] Rodillas y espinillas: %c[0,170,170,170]V\n%c[0,93,0,116] - %c[0,140,140,140] Pies: %c[0,170,170]V</text>
	</string>
	
	<string id="merc_heavy_outfit_name">
		<text>Armadura pesada (Mercenarios)</text>
	</string>
	<string id="merc_heavy_outfit_description">
		<text>El traje de armadura pesada tiene un aspecto similar al de un exoesqueleto, pero la primera y principal diferencia que llama la atencion es la ausencia de casco y de servos en los brazos y las piernas, asi como de una bateria en la espalda. Debido a esta diferencia, un traje blindado pesado es mas ligero que un exoesqueleto y tambien permite a su portador correr. A pesar de su popularidad, el traje nunca recibio su nombre. \N - %c[0,170,170,170]CARACTERISTICAS:\N-[0,153,255,255] - %c[0,140,140,140] armadura pesada \N-[0,170,170,170]Clase de armadura: \N - %c[0,93,0,116] - %c[0,140,140,140] Cabeza: %c[0,170,170,170]none\n%c[0,93,0,116] - %c[0,140,140] Ojos: %c[0,170,170,170]absent\n%c[0,93,0,116] - %c[0,140,140,140] Menton: %c[0,170,170,170]absent\n%c[0,93,0,116] - %c[0,140,140,140] Cuello: %c[0,170,170,170]absent\n%c[0,93,0,116] - %c[0,140,140,140] Torso: %c[0,170,170,170]V\n%c[0,93,0,116] - %c[0,140,140,140] Hombros: %c[0,170,170,170]V\n%c[0,93,0,116] - %c[0,140,140,140] Pinceles: %c[0,170,170,170]IV\n%c[0,93,0,116] - %c[0,140,140,140] Brazos: %c[0,170,170,IV\n%c[0,93,0,116] - %c[0,140,140,140] Caderas: %c[0,170,170,170]V\n%c[0,93,0,116] - %c[0,140,140] Rodillas y espinillas: %c[0,170,170]V\n%c[0,93,0,116] - %c[0,140,140] Pies: %c[0,170,170,170]V\n%c[0,170,170,170]PIES:\n%c[0,100,0,15] - %c[0,140,140,140,140]Proteccion contra explosiones aumentada</text>
	</string>
	
	<string id="bandit_heavy_outfit_name">
		<text>Armadura pesada (Bandidos)</text>
	</string>
	<string id="bandit_heavy_outfit_description">
		<text>El traje de armadura pesada tiene un aspecto similar al de un exoesqueleto, pero la primera y principal diferencia que llama la atencion es la ausencia de casco y de servos en los brazos y las piernas, asi como de una bateria en la espalda. Debido a esta diferencia, un traje blindado pesado es mas ligero que un exoesqueleto y tambien permite a su portador correr. A pesar de su popularidad, el traje nunca recibio su nombre. \N - %c[0,170,170,170]CARACTERISTICAS:\N-[0,153,255,255] - %c[0,140,140,140] armadura pesada \N-[0,170,170,170]Clase de armadura: \N - %c[0,93,0,116] - %c[0,140,140,140] Cabeza: %c[0,170,170,170]none\n%c[0,93,0,116] - %c[0,140,140] Ojos: %c[0,170,170,170]absent\n%c[0,93,0,116] - %c[0,140,140,140] Menton: %c[0,170,170,170]absent\n%c[0,93,0,116] - %c[0,140,140,140] Cuello: %c[0,170,170,170]absent\n%c[0,93,0,116] - %c[0,140,140,140] Torso: %c[0,170,170,170]V\n%c[0,93,0,116] - %c[0,140,140,140] Hombros: %c[0,170,170,170]V\n%c[0,93,0,116] - %c[0,140,140,140] Pinceles: %c[0,170,170,170]IV\n%c[0,93,0,116] - %c[0,140,140,140] Brazos: %c[0,170,170,IV\n%c[0,93,0,116] - %c[0,140,140,140] Caderas: %c[0,170,170,170]V\n%c[0,93,0,116] - %c[0,140,140] Rodillas y espinillas: %c[0,170,170]V\n%c[0,93,0,116] - %c[0,140,140] Pies: %c[0,170,170,170]V\n%c[0,170,170,170]PIES:\n%c[0,100,0,15] - %c[0,140,140,140] capacidad de carga aumentada</text>
	</string>
	
	<string id="military_heavy_outfit_name">
		<text>Traje blindado pesado (Ejercito)</text>
	</string>
	<string id="military_heavy_outfit_description">
		<text>El traje de armadura pesada tiene un aspecto similar al de un exoesqueleto, pero la primera y principal diferencia que llama la atencion es la ausencia de casco y de servos en los brazos y las piernas, asi como de una bateria en la espalda. Debido a esta diferencia, un traje blindado pesado es mas ligero que un exoesqueleto y tambien permite a su portador correr. A pesar de su popularidad, el traje nunca recibio su nombre. \N - %c[0,170,170,170]CARACTERISTICAS:\N-[0,153,255,255] - %c[0,140,140,140] armadura pesada \N-[0,170,170,170]Clase de armadura: \N - %c[0,93,0,116] - %c[0,140,140,140] Cabeza: %c[0,170,170,170]none\n%c[0,93,0,116] - %c[0,140,140] Ojos: %c[0,170,170,170]absent\n%c[0,93,0,116] - %c[0,140,140,140] Menton: %c[0,170,170,170]absent\n%c[0,93,0,116] - %c[0,140,140,140] Cuello: %c[0,170,170,170]absent\n%c[0,93,0,116] - %c[0,140,140,140] Torso: %c[0,170,170,170]V\n%c[0,93,0,116] - %c[0,140,140,140] Hombros: %c[0,170,170,170]V\n%c[0,93,0,116] - %c[0,140,140,140] Pinceles: %c[0,170,170,170]IV\n%c[0,93,0,116] - %c[0,140,140,140] Brazos: %c[0,170,170,IV\n%c[0,93,0,116] - %c[0,140,140,140] Caderas: %c[0,170,170,170]V\n%c[0,93,0,116] - %c[0,140,140] Rodillas y espinillas: %c[0,170,170]V\n%c[0,93,0,116] - %c[0,140,140] Pies: %c[0,170,170,170]V\n%c[0,170,170,170]PIES:\n%c[0,100,0,15] - %c[0,140,140,140,140] aumento del parametro "Shock Gain"</text>
	</string>
	
	<string id="csky_heavy_outfit_csky_name">
		<text>Armadura pesada</text>
	</string>
	<string id="csky_heavy_outfit_csky_description">
		<text>La pesada armadura tiene un aspecto similar al de un exoesqueleto, pero la primera y principal diferencia que llama la atencion es la ausencia de casco y de servos en los brazos y las piernas, asi como de una bateria en la espalda. Debido a esta diferencia, un traje de armadura pesada es mas ligero que un exoesqueleto y tambien permite a su portador correr. A pesar de su popularidad, el traje nunca recibio su nombre. \N - %c[0,170,170,170]CARACTERISTICAS:\N-[0,153,255,255] - %c[0,140,140,140] armadura pesada \N-[0,170,170,170]Clase de armadura: \N - %c[0,93,0,116] - %c[0,140,140,140] Cabeza: %c[0,170,170,170]none\n%c[0,93,0,116] - %c[0,140,140] Ojos: %c[0,170,170,170]absent\n%c[0,93,0,116] - %c[0,140,140,140] Menton: %c[0,170,170,170]absent\n%c[0,93,0,116] - %c[0,140,140,140] Cuello: %c[0,170,170,170]absent\n%c[0,93,0,116] - %c[0,140,140,140] Torso: %c[0,170,170,170]V\n%c[0,93,0,116] - %c[0,140,140,140] Hombros: %c[0,170,170,170]V\n%c[0,93,0,116] - %c[0,140,140,140] Muneca: %c[0,170,170,170]IV\n%c[0,93,0,116] - %c[0,140,140] Brazos: %c[0,170,170,170]IV\n%c[0,93,0,116] - %c[0,140,140,140] Caderas: %c[0,170,170,170]V\n%c[0,93,0,116] - %c[0,140,140,140] Rodillas y espinillas: %c[0,170,170,170]V\n%c[0,93,0,116] - %c[0,140,140,140] Pies: %c[0,170,170,170]V\n%c[0,170,170,170]V\n%c[0,100,0,15] - %c[0,140,140,140] aumento del numero de anexos para los modulos adicionales</text>
	</string>
	
	<string id="specops_duty_outfit_name">
		<text>Traje blindado Beryl-5M (Deber)</text>
	</string>
	<string id="specops_duty_outfit_description">
		<text>Modificado para operaciones en la Zona, el chaleco antibalas del ejercito de la serie PS5 con revestimiento de berilio, que ha sido mejorado por los artesanos de Deber. Esta disenado para las operaciones de asalto en las zonas con alto fondo de radiacion, pero es ineficaz en las condiciones de alta actividad anomala. Utilizado por los Stalkers a traves de los militares que cambian el equipo del ejercito por bienes barbaros. Estan equipados con soportes para modulos adicionales. \N - %c[0,140,140,140] proteccion de armadura mejorada \N - Clase de proteccion de armadura:\N - %c[0,93,0,116] - %c[0,140,140,140] Torso: %c[0,170,170,170]III\n%c[0,93,0,116] - %c[0,140,140,140] Hombros: %c[0,170,170,170]III\n%c[0,93,0,116] - %c[0,140,140,140] Muneca: %c[0,170,170,170]IIIA\n%c[0,93,0,116] - %c[0,140,140] Brazos: %c[0,170,170,170]II\n%c[0,93,0,116] - %c[0,140,140,140] Caderas: %c[0,170,170,170]II\n%c[0,93,0,116] - %c[0,140,140,140] Rodillas y espinillas: %c[0,170,170,170]III\n%c[0,93,0,116] - %c[0,140,140,140] Pies: %c[0,170,170,170]III\n \n%c[0,170,170,170]CARACTERISTICAS:\n%c[0,100,0,15] - %c[0,140,140,140,140] mayor capacidad de carga, resistencia a las balas, proteccion contra explosiones y estallidos</text>
	</string>
	
	<string id="mod_exo_proto_outfit_name">
		<text>El protoexoesqueleto Sunset M2</text>
	</string>
	<string id="mod_exo_proto_outfit_description">
		<text>Traje estandar de Zarya con servotraje de modificacion M2. La proteccion general es la misma que la del Zarya estandar, pero el peso portatil aumenta considerablemente. En comparacion con el protoexoesqueleto estandar, tiene mas peso, pero tambien una mayor capacidad de carga y una mayor proteccion contra la radiacion. Tambien es mucho mas facil correr. \N - %c[0,170,170,170]CARACTERISTICAS:\N - %c[0,153,255,255] - %c[0,140,140,140] proteccion de armadura pesada\n%c[0,153,255,255] - %c[0,140,140,140] exoesqueleto \N - %c[0,93,0,116] - %c[0,140,140,140] Torso: %c[0,170,170,170]V\n%c[0,93,0,116] - %c[0,140,140] Hombros: %c[0,170,170,170]V\n%c[0,93,0,116] - %c[0,140,140,140] Munecas: %c[0,170,170,170]V\n%c[0,93,0,116] - %c[0,140,140] Brazos: %c[0,170,170,170]V\n%c[0,93,0,116] - %c[0,140,140] Caderas: %c[0,170,170,170]V\n%c[0,93,0,116] - %c[0,140,140,140] Rodillas y espinillas: %c[0,170,170,V\n%c[0,93,0,116] - %c[0,140,140] Pies: %c[0,170,170,170]V</text>
	</string>
	
	<string id="bandit_mod_exo_proto_outfit_name">
		<text>protoexoesqueleto Sunset M2 Bandit</text>
	</string>
	
	<string id="bandit_mod_exo_proto_outfit_1_name">
		<text>Raiders proto-exoesqueleto Sunset M2</text>
	</string>
	
	<string id="dolg_mod_exo_proto_outfit_name">
		<text>Protoesqueleto naranja "Sunset M2" (Deber)</text>
	</string>
	
	<string id="dolg_mod_exo_proto_outfit_1_name">
		<text>El protoexoesqueleto Sunset M2 (Deber)</text>
	</string>
	
	<string id="dolg_mod_exo_proto_outfit_2_name">
		<text>Protoesqueleto de camuflaje Zakat M2 (Deber)</text>
	</string>
	
	<string id="dolg_mod_exo_proto_outfit_3_name">
		<text>Protoesqueleto oscuro "Sunset M2" (Deber)</text>
	</string>
	
	<string id="ecolog_mod_exo_proto_outfit_name">
		<text>El protoexoesqueleto Sunset M2 (Ecologistas)</text>
	</string>
	
	<string id="ecolog_mod_exo_proto_outfit_1_name">
		<text>Un protoexoesqueleto alternativo, Sunset M2. (Ecologistas)</text>
	</string>
	
	<string id="mod_exo_proto_outfit_1_name">
		<text>Protoesqueleto de camuflaje Zakat M2</text>
	</string>
	
	<string id="mod_exo_proto_outfit_2_name">
		<text>Protoesqueleto negro "Sunset M2"</text>
	</string>
	
	<string id="mod_exo_proto_outfit_3_name">
		<text>Protoesqueleto Zakat M2 en camuflaje de pantano</text>
	</string>
	
	<string id="mod_exo_proto_outfit_4_name">
		<text>Protoexoesqueleto Zakat M2 en camuflaje forestal</text>
	</string>
	
	<string id="mod_exo_proto_outfit_5_name">
		<text>Protoesqueleto Zakat M2 en camuflaje de otono</text>
	</string>
	
	<string id="mod_exo_proto_outfit_6_name">
		<text>Protoexoesqueleto Zakat M2 en camuflaje forestal oscuro</text>
	</string>
	
	<string id="mod_exo_proto_outfit_7_name">
		<text>Protoexoesqueleto marron "Sunset M2"</text>
	</string>
	
	<string id="mod_exo_proto_outfit_8_name">
		<text>Protoexoesqueleto Zakat M2 en camuflaje urbano</text>
	</string>
	
	<string id="mod_exo_proto_outfit_9_name">
		<text>Protoesqueleto de camuflaje Zakat M2</text>
	</string>
	
	<string id="mod_exo_proto_outfit_10_name">
		<text>Protoexoesqueleto Zakat M2 en camuflaje de bosque otonal</text>
	</string>
	
	<string id="freedom_mod_exo_proto_outfit_name">
		<text>Protoesqueleto de camuflaje Zakat M2 (Libertad)</text>
	</string>
	
	<string id="freedom_mod_exo_proto_outfit_1_name">
		<text>Protoexoesqueleto Zakat M2 en camuflaje forestal (Libertad)</text>
	</string>

	<string id="freedom_mod_exo_proto_outfit_2_name">
		<text>Protoexoesqueleto Zakat M2 en camuflaje tradicional Liberty</text>
	</string>
	
	<string id="freedom_mod_exo_proto_outfit_3_name">
		<text>Protoesqueleto Zakat M2 en camuflaje (Libertad)</text>
	</string>
	
	<string id="freedom_mod_exo_proto_outfit_4_name">
		<text>El protoexoesqueleto Sunset M2 (Libertad)</text>
	</string>
	
	<string id="freedom_mod_exo_proto_outfit_5_name">
		<text>Protoesqueleto Zakat M2 en camuflaje de pantano (Libertad)</text>
	</string>
	
	<string id="merc_mod_exo_proto_outfit_name">
		<text>El protoexoesqueleto Sunset M2 (Mercenarios)</text>
	</string>
	
	<string id="merc_mod_exo_proto_outfit_1_name">
		<text>Protoesqueleto negro "Sunset M2" (Mercenarios)</text>
	</string>
	
	<string id="Trajelith_mod_exo_proto_outfit_name">
		<text>El protoexoesqueleto Sunset M2 (Trajelito)</text>
	</string>
	
	<string id="Trajelith_mod_exo_proto_outfit_1_name">
		<text>Protoexoesqueleto Zakat M2 en camuflaje urbano (Trajelito)</text>
	</string>
	
	<string id="Trajelith_mod_exo_proto_outfit_2_name">
		<text>Protoesqueleto Zakat M2 en camuflaje de otono (Trajelito)</text>
	</string>
	
	<string id="Trajelith_mod_exo_proto_outfit_3_name">
		<text>Protoexoesqueleto marron "Sunset M2" (Trajelito)</text>
	</string>
	
	<string id="Trajelith_mod_exo_proto_outfit_4_name">
		<text>Protoesqueleto verde "Sunset M2" (Trajelito)</text>
	</string>
	
	<string id="Trajelith_mod_exo_proto_outfit_5_name">
		<text>Protoexoesqueleto desconocido Sunset M2 (Trajelito)</text>
	</string>
	
	<string id="csky_mod_exo_proto_outfit_name">
		<text>El protoexoesqueleto Sunset M2 (Cielo despejado)</text>
	</string>
	
	<string id="csky_mod_exo_proto_outfit_1_name">
		<text>Protoesqueleto Zakat M2 en camuflaje tradicional (Cielo despejado)</text>
	</string>
	
	<string id="military_mod_exo_proto_outfit_name">
		<text>Protoesqueleto del ejercito Zakat M2</text>
	</string>
	
	<string id="military_mod_exo_proto_outfit_1_name">
		<text>Protoesqueleto militar de camuflaje Zakat M2</text>
	</string>
	
	<string id="stalker_outfit_travel_name">
		<text>Traje de "turista"</text>
	</string>
	<string id="stalker_outfit_travel_description">
		<text>El traje es una combinacion de un tejido de goma de dos capas con acolchado de plexiglas y un chaleco antibalas integrado, asi como una descarga adicional. A pesar de que el chaleco antibalas es atravesado incluso por una bala de pistola, el traje es muy comun debido a su baratura y a su amplio margen de mejora. Equipado con soportes incorporados para modulos adicionales. \N - %c[0,170,170,170]CARACTERISTICAS:\N-[0,153,255,255] - %c[0,140,140,140] armadura ligera \N-[0,170,170,170]CLASE DE PROTECCION DE LA ARMADURA:\N-[0,93,0,116] - %c[0,140,140,140] Torso: %c[0,170,170,170]IIIA\n%c[0,93,0,116] - %c[0,140,140,140] Hombros:%c[0,170,170,170]IIIA\n%c[0,93,0,116] - %c[0,140,140] Muneca:%c[0,170,170,170]II\n%c[0,93,0,116] - %c[0,140,140] Brazos: %c[0,170,170,170]none\n%c[0,93,0,116] - %c[0,140,140,140] Caderas: %c[0,170,170,170]II\n%c[0,93,0,116] - %c[0,140,140,140] Rodillas y espinillas: %c[0,170,170,170]II\n%c[0,93,0,116] - %c[0,140,140,140] Pies: %c[0,170,170,170]IIIA\n%c[0,170,170,170]PIES:\n%c[0,100,0,15] - %c[0,140,140,140] mayor resistencia al desgaste</text>
	</string>
	
	<string id="stalker_outfit_travel_1_name">
		<text>traje turistico de camuflaje de tundra</text>
	</string>
	
	<string id="stalker_outfit_travel_2_name">
		<text>Traje marron "Turista"</text>
	</string>
	
	<string id="stalker_outfit_travel_3_name">
		<text>Traje del ejercito "Turista"</text>
	</string>
	
	<string id="stalker_outfit_travel_4_name">
		<text>Traje negro del ejercito "Turista"</text>
	</string>
	
	<string id="stalker_outfit_travel_5_name">
		<text>Traje turistico con armadura negra</text>
	</string>
	
	<string id="stalker_outfit_travel_6_name">
		<text>Traje turistico de camuflaje forestal</text>
	</string>
	
	<string id="stalker_outfit_travel_7_name">
		<text>Traje de trabajo "turistico" en camuflaje otonal</text>
	</string>
	
	<string id="stalker_outfit_travel_8_name">
		<text>Traje de camuflaje marron para turistas</text>
	</string>
	
	<string id="stalker_outfit_travel_9_name">
		<text>Traje turistico de camuflaje urbano</text>
	</string>
	
	<string id="stalker_outfit_travel_10_name">
		<text>Traje turistico de camuflaje oscuro</text>
	</string>
	
	<string id="stalker_outfit_travel_11_name">
		<text>Traje turistico de camuflaje marron oscuro</text>
	</string>
	
	<string id="stalker_outfit_travel_12_name">
		<text>Traje de trabajo "turistico" de camuflaje militar</text>
	</string>
	
	<string id="stalker_outfit_travel_bandit_name">
		<text>Traje de bandido "Turista"</text>
	</string>
	<string id="stalker_outfit_travel_bandit_description">
		<text>El traje es una combinacion de un tejido de goma de dos capas con acolchado de plexiglas y un chaleco antibalas integrado, asi como una descarga adicional. A pesar de que el chaleco antibalas es atravesado incluso por una bala de pistola, el traje es muy comun debido a su baratura y a su amplio margen de mejora. Equipado con soportes incorporados para modulos adicionales. Modificado por los artesanos del gangster. \N - %c[0,170,170,170]CARACTERISTICAS:\N-[0,153,255,255] - %c[0,140,140,140] proteccion de armadura ligera \N-[0,170,170,170]Clase de proteccion de armadura:\N-[0,93,0,116] - %c[0,140,140,140] Thors: %c[0,170,170,170]IIIA\n%c[0,93,0,116] - %c[0,140,140,140] Hombros:%c[0,170,170,170]IIIA\n%c[0,93,0,116] - %c[0,140,140] Muneca:%c[0,170,170,170]II\n%c[0,93,0,116] - %c[0,140,140] Brazos: %c[0,170,170,170]none\n%c[0,93,0,116] - %c[0,140,140,140] Caderas: %c[0,170,170,170]II\n%c[0,93,0,116] - %c[0,140,140,140] Rodillas y espinillas: %c[0,170,170,170]II\n%c[0,93,0,116] - %c[0,140,140,140] Pies: %c[0,170,170,170]IIIA\n%c[0,170,170,170]PIES:\n%c[0,100,0,15] - %c[0,140,140,140] mayor capacidad de carga</text>
	</string>
	
	<string id="stalker_outfit_travel_bandit_1_name">
		<text>Рейдерский комбинезон «Турист»</text>
	</string>
	
	<string id="stalker_outfit_travel_bandit_2_name">
		<text>Traje oscuro "Turista"</text>
	</string>
	
	<string id="stalker_outfit_travel_dolg_name">
		<text>Traje naranja "Turista" (Deber)</text>
	</string>
	<string id="stalker_outfit_travel_dolg_description">
		<text>El traje es una combinacion de un tejido de goma de dos capas con acolchado de plexiglas y un chaleco antibalas integrado, asi como una descarga adicional. A pesar de que el chaleco antibalas es atravesado incluso por una bala de pistola, el traje es muy comun debido a su baratura y a su amplio margen de mejora. Esta equipado con fijaciones incorporadas para modulos adicionales. Modificado por los artesanos de Deber. \N - %c[0,170,170,170]CARACTERISTICAS:\N-[0,153,255,255] - %c[0,140,140,140] armadura ligera \N-[0,170,170,170]CLASE DE PROTECCION DE LA ARMADURA:\N-[0,93,0,116] - %c[0,140,140,140,140] Thors: %c[0,170,170,170]IIIA\n%c[0,93,0,116] - %c[0,140,140,140] Hombros:%c[0,170,170,170]IIIA\n%c[0,93,0,116] - %c[0,140,140] Muneca:%c[0,170,170,170]II\n%c[0,93,0,116] - %c[0,140,140] Brazos: %c[0,170,170,170]none\n%c[0,93,0,116] - %c[0,140,140,140] Caderas: %c[0,170,170,170]II\n%c[0,93,0,116] - %c[0,140,140,140] Rodillas y espinillas: %c[0,170,170,170]II\n%c[0,93,0,116] - %c[0,140,140,140] Pies: %c[0,170,170,170]IIIA\n%c[0,170,170,170]CARACTERISTICAS:\n%c[0,100,0,15] - %c[0,140,140,140] proteccion mejorada contra explosiones y desgarros</text>
	</string>
	
	<string id="stalker_outfit_travel_dolg_1_name">
		<text>traje de turista (Deber)</text>
	</string>
	
	<string id="stalker_outfit_travel_dolg_2_name">
		<text>Traje de camuflaje "Turista" (Deber)</text>
	</string>
	
	<string id="stalker_outfit_travel_dolg_3_name">
		<text>Traje oscuro "Turista" (Deber)</text>
	</string>
	
	<string id="stalker_outfit_travel_ecologist_name">
		<text>Traje oscuro "Turista" (Ecologistas)</text>
	</string>
	<string id="stalker_outfit_travel_ecologist_description">
		<text>El traje es una combinacion de un tejido de goma de dos capas con acolchado de plexiglas y un chaleco antibalas integrado, asi como una descarga adicional. A pesar de que el chaleco antibalas es atravesado incluso por una bala de pistola, el traje es muy comun debido a su baratura y a su amplio margen de mejora. Equipado con soportes incorporados para modulos adicionales. Mejorado por las tecnicas cientificas. \n \n%c[0,170,170,170]CARACTERISTICAS:\n%c[0,153,255,255] - %c[0,140,140,140] armadura ligera \n \n%c[0,170,170,170]Clase de armadura:\n%c[0,93,0,116] - %c[0,140,140,140] Thors: %c[0,170,170,170]IIIA\n%c[0,93,0,116] - %c[0,140,140,140] Hombros:%c[0,170,170,170]IIIA\n%c[0,93,0,116] - %c[0,140,140] Muneca:%c[0,170,170,170]II\n%c[0,93,0,116] - %c[0,140,140] Brazos: %c[0,170,170,170]none\n%c[0,93,0,116] - %c[0,140,140,140] Caderas: %c[0,170,170,170]II\n%c[0,93,0,116] - %c[0,140,140,140] Rodillas y espinillas: %c[0,170,170,170]II\n%c[0,93,0,116] - %c[0,140,140,140] Pies: %c[0,170,170,170]IIIA\n%c[0,170,170,170]CARACTERISTICAS:\n%c[0,100,0,15] - %c[0,140,140,140,140] proteccion mejorada contra descargas electricas y productos quimicos</text>
	</string>
	
	<string id="stalker_outfit_travel_ecologist_1_name">
		<text>Traje de "turista" (Ecologistas)</text>
	</string>
	
	<string id="stalker_outfit_travel_ecologist_2_name">
		<text>Traje ligero "Turista" (Ecologistas)</text>
	</string>
	
	<string id="stalker_outfit_travel_ecologist_3_name">
		<text>Traje "turistico" de los guardias ecologistas</text>
	</string>
	
	<string id="stalker_outfit_travel_freedom_name">
		<text>Traje de trabajo "turistico" en camuflaje otonal (Libertad)</text>
	</string>
	<string id="stalker_outfit_travel_freedom_description">
		<text>El traje es una combinacion de un tejido de goma de dos capas con acolchado de plexiglas y un chaleco antibalas integrado, asi como una descarga adicional. A pesar de que el chaleco antibalas es atravesado incluso por una bala de pistola, el traje es muy comun debido a su baratura y a su amplio margen de mejora. Equipado con soportes incorporados para modulos adicionales. Modificado por los artesanos de Liberty. \N - %c[0,170,170,170]CARACTERISTICAS:\N-[0,153,255,255] - %c[0,140,140,140] proteccion de armadura ligera \N-[0,170,170,170]Clase de proteccion de armadura:\N-[0,93,0,116] - %c[0,140,140,140] Thors: %c[0,170,170,170]IIIA\n%c[0,93,0,116] - %c[0,140,140,140] Hombros:%c[0,170,170,170]IIIA\n%c[0,93,0,116] - %c[0,140,140] Muneca:%c[0,170,170,170]II\n%c[0,93,0,116] - %c[0,140,140] Brazos: %c[0,170,170,170]none\n%c[0,93,0,116] - %c[0,140,140,140] Caderas: %c[0,170,170,170]II\n%c[0,93,0,116] - %c[0,140,140,140] Rodillas y espinillas: %c[0,170,170,170]II\n%c[0,93,0,116] - %c[0,140,140,140] Pies: %c[0,170,170,170]IIIA\n%c[0,170,170,170]PIES:\n%c[0,100,0,15] - %c[0,140,140,140] peso reducido del traje</text>
	</string>
	
	<string id="stalker_outfit_travel_freedom_1_name">
		<text>Traje de trabajo "turistico" en camuflaje de pantano (Libertad)</text>
	</string>
	
	<string id="stalker_outfit_travel_freedom_2_name">
		<text>Traje turistico de camuflaje Flecktarn (Libertad)</text>
	</string>
	
	<string id="stalker_outfit_travel_freedom_3_name">
		<text>Traje de "turista". (Libertad)</text>
	</string>
	
	<string id="stalker_outfit_travel_freedom_4_name">
		<text>Traje turistico de camuflaje tradicional (Libertad)</text>
	</string>
	
	<string id="stalker_outfit_travel_freedom_5_name">
		<text>Traje de turista en camuflaje forestal (Libertad)</text>
	</string>
	
	<string id="stalker_outfit_travel_freedom_6_name">
		<text>Traje "turistico" de camuflaje militar (Libertad)</text>
	</string>
	
	<string id="merc_outfit_travel_name">
		<text>Traje de "turista" (Mercenarios)</text>
	</string>
	<string id="merc_outfit_travel_description">
		<text>Комбинезон представляет собой сочетание двухслойной прорезиненной ткани с плексигласовой прокладкой и встроенного бронежилета, а также дополнительной разгрузки. Несмотря на то, что бронежилет пробивается даже пистолетной пулей, костюм очень распространён из-за дешевизны и широких возможностей для улучшения. Оснащён встроенными креплениями для дополнительных модулей. Модифицирован умельцами Наёмников.\n \n%c[0,170,170,170]ХАРАКТЕРИСТИКИ:\n%c[0,153,255,255] • %c[0,140,140,140] лёгкая бронезащита \n \n%c[0,170,170,170]КЛАСС БРОНЕЗАЩИТЫ:\n%c[0,93,0,116] • %c[0,140,140,140] Торс: %c[0,170,170,170]IIIA\n%c[0,93,0,116] • %c[0,140,140,140] Плечи: %c[0,170,170,170]IIIA\n%c[0,93,0,116] • %c[0,140,140,140] Кисти: %c[0,170,170,170]II\n%c[0,93,0,116] • %c[0,140,140,140] Руки: %c[0,170,170,170]отсутствует\n%c[0,93,0,116] • %c[0,140,140,140] Бедра: %c[0,170,170,170]II\n%c[0,93,0,116] • %c[0,140,140,140] Колени и голень: %c[0,170,170,170]II\n%c[0,93,0,116] • %c[0,140,140,140] Ступни: %c[0,170,170,170]IIIA\n \n%c[0,170,170,170]ОСОБЕННОСТЬ:\n%c[0,100,0,15] • %c[0,140,140,140] повышена защита от взрывов</text>
	</string>
	
	<string id="merc_outfit_travel_1_name">
		<text>Traje oscuro "Turista" (Mercenarios)</text>
	</string>
	
	<string id="Trajelith_outfit_travel_name">
		<text>Traje marron "Turista" (Trajelito)</text>
	</string>
	<string id="Trajelith_outfit_travel_description">
		<text>El traje es una combinacion de un tejido de goma de dos capas con acolchado de plexiglas y un chaleco antibalas integrado, asi como una descarga adicional. A pesar de que el chaleco antibalas es atravesado incluso por una bala de pistola, el traje es muy comun debido a su baratura y a su amplio margen de mejora. Esta equipado con fijaciones incorporadas para modulos adicionales. Modificado por los artesanos de Trajelithoa. \N - %c[0,170,170,170]CARACTERISTICAS:\N-[0,153,255,255] - %c[0,140,140,140] proteccion de armadura ligera \N-[0,170,170,170]Clase de proteccion de armadura:\N-[0,93,0,116] - %c[0,140,140,140] Thors: %c[0,170,170,170]IIIA\n%c[0,93,0,116] - %c[0,140,140,140] Hombros:%c[0,170,170,170]IIIA\n%c[0,93,0,116] - %c[0,140,140] Muneca:%c[0,170,170,170]II\n%c[0,93,0,116] - %c[0,140,140] Brazos: %c[0,170,170,170]none\n%c[0,93,0,116] - %c[0,140,140,140] Caderas: %c[0,170,170,170]II\n%c[0,93,0,116] - %c[0,140,140,140] Rodillas y espinillas: %c[0,170,170,170]II\n%c[0,93,0,116] - %c[0,140,140,140] Pies: %c[0,170,170,170]IIIA\n%c[0,170,170,170]PIES:\n%c[0,100,0,15] - %c[0,140,140,140] mayor proteccion contra la radiacion</text>
	</string>
	
	<string id="Trajelith_outfit_travel_1_name">
		<text>Traje de "turista"(Trajelito)</text>
	</string>
	
	<string id="Trajelith_outfit_travel_2_name">
		<text>Комбинезон «Турист» в городском камуфляже (Trajelito)</text>
	</string>
	
	<string id="Trajelith_outfit_travel_3_name">
		<text>Traje de camuflaje "Turista" (Trajelito)</text>
	</string>
	
	<string id="csky_outfit_travel_name">
		<text>Traje verde "Turista" (Cielo despejado)</text>
	</string>
	<string id="csky_outfit_travel_description">
		<text>El traje es una combinacion de un tejido de goma de dos capas con acolchado de plexiglas y un chaleco antibalas integrado, asi como una descarga adicional. A pesar de que el chaleco antibalas es atravesado incluso por una bala de pistola, el traje es muy comun debido a su baratura y a su amplio margen de mejora. Dispone de enlaces integrados para modulos adicionales. Modificado por los artesanos de Pure Sky. \N - %c[0,170,170,170]CARACTERISTICAS:\N-[0,153,255,255] - %c[0,140,140,140] proteccion de armadura ligera \N-[0,170,170,170]Clase de proteccion de armadura:\N-[0,93,0,116] - %c[0,140,140,140] Thors: %c[0,170,170,170]IIIA\n%c[0,93,0,116] - %c[0,140,140,140] Hombros:%c[0,170,170,170]IIIA\n%c[0,93,0,116] - %c[0,140,140] Muneca:%c[0,170,170,170]II\n%c[0,93,0,116] - %c[0,140,140] Brazos: %c[0,170,170,170]none\n%c[0,93,0,116] - %c[0,140,140,140] Caderas: %c[0,170,170,170]II\n%c[0,93,0,116] - %c[0,140,140,140] Rodillas y espinillas: %c[0,170,170,170]II\n%c[0,93,0,116] - %c[0,140,140,140] Pies: %c[0,170,170,170]IIIA\n%c[0,170,170,170]CARACTERISTICAS:\n%c[0,100,0,15] - %c[0,140,140,140] aumento del numero de monturas adicionales</text>
	</string>
	
	<string id="csky_outfit_travel_1_name">
		<text>Traje de "turista" (Cielo despejado)</text>
	</string>
	
	<string id="csky_outfit_travel_2_name">
		<text>Traje de turista en camuflaje tradicional (Cielo despejado)</text>
	</string>
	
	<string id="csky_outfit_travel_3_name">
		<text>Traje verde oscuro "Turista" (Cielo despejado)</text>
	</string>
	
	<string id="csky_outfit_travel_4_name">
		<text>Traje alternativo "Turista" (Cielo despejado)</text>
	</string>
	
	<string id="army_outfit_travel_name">
		<text>Trajes de trabajo Voenstal</text>
	</string>
	<string id="army_outfit_travel_description">
		<text>\N - [0,170,170]Los Trajes son una combinacion de un tejido engomado de dos capas con acolchado de plexiglas y una armadura integrada en el cuerpo y una descarga adicional. A pesar de que el chaleco antibalas atraviesa incluso una bala de pistola, el traje es muy comun debido a su baratura y a su amplio margen de mejora. Esta equipado con fijaciones incorporadas para modulos adicionales. Modificado por tecnicos militares. \N - %c[0,170,170,170]CARACTERISTICAS:\N-[0,153,255,255] - %c[0,140,140,140] armadura ligera \N-[0,170,170,170]Clase de proteccion de la armadura:\N-[0,93,0,116] - %c[0,140,140,140] Torso: %c[0,170,170,170]IIIA\n%c[0,93,0,116] - %c[0,140,140,140] Hombros:%c[0,170,170,170]IIIA\n%c[0,93,0,116] - %c[0,140,140] Muneca:%c[0,170,170,170]II\n%c[0,93,0,116] - %c[0,140,140] Brazos: %c[0,170,170,170]none\n%c[0,93,0,116] - %c[0,140,140,140] Caderas: %c[0,170,170,170]II\n%c[0,93,0,116] - %c[0,140,140,140] Rodillas y espinillas: %c[0,170,170,170]II\n%c[0,93,0,116] - %c[0,140,140,140] Pies: %c[0,170,170,170]IIIA\n%c[0,170,170,170]Cuartos traseros:\n%c[0,100,0,15] - %c[0,140,140,140]</text>
	</string>
	
	<string id="freedom_merc_outfit_name">
		<text>El traje de las fuerzas especiales de Svoboda</text>
	</string>
	<string id="freedom_merc_outfit_description">
	<text>Trajes de Stalker de la faccion Libertad. Se basa en una muestra del equipamiento de las Fuerzas Especiales de los ejercitos occidentales. El tratamiento especial del tejido ha mejorado la resistencia del blindaje durante el desplazamiento fisico de las placas. Dispone de dos montajes de modulos incorporados. \N - %c[0,170,170,170]CARACTERISTICAS:\N-[0,153,255,255] - %c[0,140,140,140] proteccion de armadura ligera \N-[0,170,170,170]Clase de proteccion de armadura:\N-[0,93,0,116] - %c[0,140,140,140] Thors: %c[0,170,170,170]IIIA\n%c[0,93,0,116] - %c[0,140,140,140] Hombros:%c[0,170,170,170]IIIA\n%c[0,93,0,116] - %c[0,140,140] Muneca:%c[0,170,170,170]II\n%c[0,93,0,116] - %c[0,140,140] Brazos: %c[0,170,170,170]none\n%c[0,93,0,116] - %c[0,140,140,140] Caderas: %c[0,170,170,170]II\n%c[0,93,0,116] - %c[0,140,140,140] Rodillas y espinillas: %c[0,170,170,170]II\n%c[0,93,0,116] - %c[0,140,140,140] Pies: %c[0,170,170,170]IIIA\n%c[0,170,170,170]PIES:\n%c[0,100,0,15] - %c[0,140,140,140]</text>
	</string>
	
	<string id="freedom_merc_outfit_1_name">
		<text>Traje marron de las Fuerzas Especiales Liberty</text>
	</string>
	
	<string id="freedom_merc_outfit_2_name">
		<text>Traje del Servicio Forestal de las Fuerzas Especiales de la Libertad</text>
	</string>
	
	<string id="stalker_merc_outfit_name">
		<text>Traje de las Fuerzas Especiales</text>
	</string>
	<string id="stalker_merc_outfit_description">
	<text>Traje de acosador. La base esta tomada de las muestras de trajes de las Fuerzas Especiales de los ejercitos occidentales. Gracias al tratamiento especial del tejido, la resistencia de la armadura al desplazamiento fisico de las placas se ve reforzada. Dispone de dos montajes de modulos incorporados. \N - %c[0,170,170,170]CARACTERISTICAS:\N-[0,153,255,255] - %c[0,140,140,140] proteccion de armadura ligera \N-[0,170,170,170]Clase de proteccion de armadura:\N-[0,93,0,116] - %c[0,140,140,140] Thors: %c[0,170,170,170]IIIA\n%c[0,93,0,116] - %c[0,140,140,140] Hombros:%c[0,170,170,170]IIIA\n%c[0,93,0,116] - %c[0,140,140] Muneca:%c[0,170,170,170]II\n%c[0,93,0,116] - %c[0,140,140] Brazos: %c[0,170,170,170]none\n%c[0,93,0,116] - %c[0,140,140,140] Caderas: %c[0,170,170,170]II\n%c[0,93,0,116] - %c[0,140,140,140] Rodillas y espinillas: %c[0,170,170,170]II\n%c[0,93,0,116] - %c[0,140,140,140] Pies: %c[0,170,170,170]IIIA\n%c[0,170,170,170]PIES:\n%c[0,100,0,15] - %c[0,140,140,140]</text>
	</string>
	
	<string id="Trajelith_merc_outfit_name">
		<text>Conjunto de fuerzas especiales de Trajelito</text>
	</string>
	<string id="Trajelith_merc_outfit_description">
	<text>Trajes de Stalker de la faccion Trajelito. Se basa en el equipamiento de las Fuerzas Especiales de los ejercitos occidentales. Gracias al tratamiento especial del tejido, la resistencia de la armadura al desplazamiento fisico de las placas se ve reforzada. Dispone de dos montajes de modulos incorporados. \N - %c[0,170,170,170]CARACTERISTICAS:\N-[0,153,255,255] - %c[0,140,140,140] proteccion de armadura ligera \N-[0,170,170,170]Clase de proteccion de armadura:\N-[0,93,0,116] - %c[0,140,140,140] Thors: %c[0,170,170,170]IIIA\n%c[0,93,0,116] - %c[0,140,140,140] Hombros:%c[0,170,170,170]IIIA\n%c[0,93,0,116] - %c[0,140,140] Muneca:%c[0,170,170,170]II\n%c[0,93,0,116] - %c[0,140,140] Brazos: %c[0,170,170,170]none\n%c[0,93,0,116] - %c[0,140,140,140] Caderas: %c[0,170,170,170]II\n%c[0,93,0,116] - %c[0,140,140,140] Rodillas y espinillas: %c[0,170,170,170]II\n%c[0,93,0,116] - %c[0,140,140,140] Pies: %c[0,170,170,170]IIIA\n%c[0,170,170,170]PIES:\n%c[0,100,0,15] - %c[0,140,140,140]</text>
	</string>
	
	<string id="csky_light_novice_outfit_b_name">
		<text>ЧН-1б</text>
	</string>
	<string id="csky_light_novice_outfit_b_description">
		<text>Una modificacion del chaleco estandar CHN-1 especialmente para terrenos pantanosos. Este chaleco antibalas fue desarrollado para operaciones de busqueda en zonas con baja actividad anomala. El uso de materiales de alta calidad ha aumentado la resistencia al desgaste. Tiene tres fijaciones integradas para modulos adicionales. \N - %c[0,170,170,170]CARACTERISTICAS:\N-[0,153,255,255] - %c[0,140,140,140] armadura ligera \N-[0,170,170,170]CLASE DE PROTECCION DE LA ARMADURA:\N-[0,93,0,116] - %c[0,140,140,140,140] Thors: %c[0,170,170,170]IIIA\n%c[0,93,0,116] - %c[0,140,140,140] Hombros:%c[0,170,170,170]IIIA\n%c[0,93,0,116] - %c[0,140,140] Muneca:%c[0,170,170,170]II\n%c[0,93,0,116] - %c[0,140,140] Brazos: %c[0,170,170,170]none\n%c[0,93,0,116] - %c[0,140,140,140] Caderas: %c[0,170,170,170]II\n%c[0,93,0,116] - %c[0,140,140,140] Rodillas y espinillas: %c[0,170,170,170]II\n%c[0,93,0,116] - %c[0,140,140,140] Pies: %c[0,170,170,170]IIIA\n \n%c[0,170,170,170]CARACTERISTICAS:\n%c[0,100,0,15] - %c[0,140,140,140] aumento del numero de anexos para los modulos adicionales</text>
	</string>
	
		<string id="exo_proto_outfit_dolg_name">
		<text>Protoexoesqueleto PS5-M</text>
	</string>
	
	<string id="exo_proto_outfit_freedom_name">
		<text>Protoexoesqueleto de Freedom Guardian</text>
	</string>
	
	<string id="exo_proto_outfit_merc_name">
		<text>Protoexoesqueleto mercenario</text>
	</string>
	
	<string id="exo_proto_outfit_Trajelith_name">
		<text>Protoexoesqueleto Granite M1</text>
	</string>
	
	<string id="exo_proto_outfit_isg_name">
		<text>Proto-exoesqueleto del I.I.G.</text>
	</string>
	
	<string id="exo_proto_outfit_bandit_name">
		<text>Protoexoesqueleto Raider</text>
	</string>
	
	<string id="exo_proto_outfit_bandit_1_name">
		<text>Protoexoesqueleto del Angel Oscuro</text>
	</string>
	
	<string id="exo_proto_outfit_bandit_2_name">
		<text>Protoexoesqueleto Onyx</text>
	</string>
	
	<string id="exo_proto_outfit_dolg_1_name">
		<text>Protoexoesqueleto PS5-M2</text>
	</string>
	
	<string id="exo_proto_outfit_dolg_2_name">
		<text>Protoexoesqueleto PS5-M2 «Deber»</text>
	</string>
	
	<string id="exo_proto_outfit_dolg_3_name">
		<text>Protoesqueleto naranja PS5-M2</text>
	</string>
	
	<string id="exo_proto_outfit_dolg_4_name">
		<text>Protoesqueleto de camuflaje PS5-M2</text>
	</string>
	
	<string id="exo_proto_outfit_dolg_5_name">
		<text>Protoexoesqueleto PS5-M2 en camuflaje urbano</text>
	</string>
	
	<string id="exo_proto_outfit_ecologist_name">
		<text>Protoexoesqueleto "Ecologista"</text>
	</string>
	
	<string id="exo_proto_outfit_ecologist_1_name">
		<text>El protoexoesqueleto Sunset</text>
	</string>
	
	<string id="exo_proto_outfit_freedom_1_name">
		<text>Protoexoesqueleto Freedom Wind</text>
	</string>
	
	<string id="exo_proto_outfit_freedom_2_name">
		<text>Protoexoesqueleto Swamp Wind</text>
	</string>

	<string id="exo_proto_outfit_freedom_3_name">
		<text>Protoexoesqueleto de camuflaje del Guardian de la Libertad</text>
	</string>

	<string id="exo_proto_outfit_freedom_4_name">
		<text>El protoexoesqueleto forestal "Guardian de la Libertad"</text>
	</string>	
	
	<string id="exo_proto_outfit_freedom_5_name">
		<text>Protoexoesqueleto de caza del Guardian de la Libertad</text>
	</string>
	
	<string id="exo_proto_outfit_merc_1_name">
		<text>Protoexoesqueleto de Crepusculo</text>
	</string>
	
	<string id="exo_proto_outfit_merc_2_name">
		<text>Protoexoesqueleto Dark Sunset</text>
	</string>
	
	<string id="exo_proto_outfit_merc_3_name">
		<text>Protoexoesqueleto PS5-M2 Mercenary</text>
	</string>
	
	<string id="exo_proto_outfit_Trajelith_1_name">
		<text>Protoexoesqueleto "Preacher"</text>
	</string>
	
	<string id="exo_proto_outfit_Trajelith_2_name">
		<text>Protoexoesqueleto Sinner</text>
	</string>
	
	<string id="exo_proto_outfit_Trajelith_3_name">
		<text>Protoexoesqueleto del Trajepolio de los Guardianes</text>
	</string>
	
	<string id="exo_proto_outfit_Trajelith_4_name">
		<text>Protoexoesqueleto Granite M3</text>
	</string>
	
	<string id="exo_proto_outfit_Trajelith_5_name">
		<text>Protoexoesqueleto "novato"</text>
	</string>
	
	<string id="exo_proto_outfit_csky_name">
		<text>Protoexoesqueleto de Dawn</text>
	</string>
	
	<string id="exo_proto_outfit_csky_1_name">
		<text>Protoexoesqueleto «Cielo despejado»</text>
	</string>
	
	<string id="exo_proto_outfit_1_name">
		<text>Protoexoesqueleto Stalker</text>
	</string>
	
	<string id="exo_proto_outfit_2_name">
		<text>Protoexoesqueleto Marauder</text>
	</string>
	
	<string id="exo_proto_outfit_3_name">
		<text>Protoexoesqueleto de caza</text>
	</string>
	
	<string id="exo_proto_outfit_4_name">
		<text>Protoexoesqueleto de camuflaje</text>
	</string>
	
	<string id="exo_proto_outfit_5_name">
		<text>Protoexoesqueleto de pantano</text>
	</string>
	
	<string id="exo_proto_outfit_6_name">
		<text>Protoexoesqueleto del explorador</text>
	</string>
	
	<string id="exo_proto_outfit_7_name">
		<text>Protoexoesqueleto "Putnik"</text>
	</string>
	
	<string id="exo_proto_outfit_military_name">
		<text>Protoesqueleto de camuflaje del ejercito</text>
	</string>
	
	<string id="exo_proto_outfit_military_1_name">
		<text>Protoexoesqueleto del ejercito oscuro</text>
	</string>
	
	<string id="exo_proto_outfit_military_2_name">
		<text>Protoexoesqueleto del ejercito</text>
	</string>
	
	<string id="novice_outfit_1_name">
		<text>Chaqueta de caza</text>
	</string>
	
	<string id="novice_outfit_2_name">
		<text>Chaqueta de camuflaje</text>
	</string>
	
	<string id="novice_outfit_3_name">
		<text>Chaqueta de cuadros</text>
	</string>
	
	<string id="novice_outfit_4_name">
		<text>Chaqueta del ejercito</text>
	</string>
	
	<string id="novice_outfit_5_name">
		<text>Chaqueta de cuero verde</text>
	</string>
	
	<string id="novice_outfit_6_name">
		<text>Chaqueta de cuero roja</text>
	</string>
	
	<string id="novice_outfit_1m_name">
		<text>Chaqueta de caza con capucha</text>
	</string>
	
	<string id="novice_outfit_2m_name">
		<text>Chaqueta con capucha de camuflaje</text>
	</string>
	
	<string id="novice_outfit_3m_name">
		<text>Chaqueta con capucha a cuadros</text>
	</string>
	
	<string id="novice_outfit_4m_name">
		<text>Chaqueta con capucha del ejercito</text>
	</string>
	
	<string id="novice_outfit_5m_name">
		<text>Chaqueta de cuero verde con capucha</text>
	</string>
	
	<string id="novice_outfit_6m_name">
		<text>Chaqueta de cuero verde con capucha</text>
	</string>
	
	<string id="stalker_outfit_name_1">
		<text>Zarya marron.</text>
	</string>
	
	<string id="stalker_outfit_name_2">
		<text>"Amanecer Celestial"</text>
	</string>
	
	<string id="stalker_outfit_name_3">
		<text>Camuflaje "Zarya"</text>
	</string>
	
	<string id="stalker_outfit_name_4">
		<text>Caza de "Zarya"</text>
	</string>
	
	<string id="stalker_outfit_name_5">
		<text>Pantano de Zarya</text>
	</string>
	
	<string id="stalker_outfit_name_6">
		<text>Ejercito Zarya</text>
	</string>
	
	<string id="stalker_outfit_name_7">
		<text>Asalto a Zarya</text>
	</string>
	
	<string id="radiation_outfit_1_name">
		<text>«Amanecer» Camuflaje digital otonal</text>
	</string>
	
	<string id="radiation_outfit_2_name">
		<text>Camuflaje «Amanecer»</text>
	</string>
	
	<string id="bandit_novice_outfit_1_name">
		<text>Una chaqueta de bandido a cuadros</text>
	</string>
	
	<string id="bandit_novice_outfit_2_name">
		<text>Una chaqueta de cuero de bandido</text>
	</string>
	
	<string id="bandit_novice_outfit_3_name">
		<text>Chaqueta de los Raiders</text>
	</string>
	
	<string id="bandit_novice_outfit_1m_name">
		<text>Chaqueta de bandido con capucha a cuadros rojos</text>
	</string>
	
	<string id="bandit_novice_outfit_2m_name">
		<text>Chaqueta de cuero de gangster con capucha</text>
	</string>
	
	<string id="bandit_novice_outfit_3m_name">
		<text>Capucha de asalto</text>
	</string>
	
	<string id="trenchcoat_outfit_1_name">
		<text>Capa oscura</text>
	</string>
	
	<string id="trenchcoat_outfit_2_name">
		<text>Capa de caza</text>
	</string>
	
	<string id="trenchcoat_outfit_3_name">
		<text>Abrigo de capa marron</text>
	</string>
	
	<string id="trenchcoat_outfit_1m_name">
		<text>Manto rojo oscuro</text>
	</string>
	
	<string id="trenchcoat_outfit_2m_name">
		<text>Capa de pantano</text>
	</string>
	
	<string id="trenchcoat_outfit_3m_name">
		<text>Capa de Pahan</text>
	</string>
	
	<string id="trenchcoat_brown_outfit_1_name">
		<text>Capa de merodeador</text>
	</string>
	
	<string id="trenchcoat_brown_outfit_2_name">
		<text>manto oscuro y denso</text>
	</string>
	
	<string id="trenchcoat_brown_outfit_3_name">
		<text>Capa de caza.</text>
	</string>
	
	<string id="trenchcoat_brown_outfit_4_name">
		<text>El denso manto de Pahan</text>
	</string>
	
	<string id="csky_novice_outfit_1_name">
		<text>Chaqueta de combate con capucha</text>
	</string>
	
	<string id="csky_light_novice_outfit_1_name">
		<text>CH-1 en camuflaje digital</text>
	</string>
	
	<string id="dolg_scientific_outfit_1_name">
		<text>Camuflaje PSZ-9Md</text>
	</string>
	
	<string id="dolg_outfit_1_name">
		<text>Naranja PS5-M</text>
	</string>
	
	<string id="dolg_exo_outfit_1_name">
		<text>Exoesqueleto de camuflaje de Deber</text>
	</string>
	
	<string id="dolg_exo_outfit_2_name">
		<text>Exoesqueleto de Deber en camuflaje digital</text>
	</string>

	<string id="soldier_izol_1_outfit_name">
		<text>Traje blindado aislante militar Gagarin</text>
	</string>
	<string id="soldier_izol_1_outfit_description">
		<text>Traje blindado aislante del ejercito "Gagarin" disenado para operaciones de asalto en condiciones extremas de la Zona. Esta equipado con un revestimiento aislante externo y un sistema de respiracion de circuito cerrado, cuyo elemento principal es una modificacion de la mascara de gas GP-17. Gracias a esta solucion se consigue una perfecta proteccion contra las influencias anomalas. La base de la proteccion del blindaje es una modificacion de la serie de chalecos Fort Redoubt T7, que proporciona una excelente proteccion contra las balas en forma de proyectil y la metralla, sin reducir la movilidad del usuario. A pesar de sus excelentes caracteristicas de proteccion desde el punto de vista del acosador, tiene las siguientes desventajas: bajo peso de transporte. Tiene tres ranuras para modulos adicionales. \N - %c[0,170,170]CARACTERISTICAS:\N - %c[0,153,255,255] - %c[0,140,140,140] proteccion de armadura mejorada\n \N - [0,170,170,170]Clase de armadura: \N - %c[0,93,0,116] - %c[0,140,140,140] Torso: %c[0,170,170,170]IV\n%c[0,93,0,116] - %c[0,140,140,140] Hombros: %c[0,170,170,170]IV\n%c[0,93,0,116] - %c[0,140,140,140] Muneca: %c[0,170,170,170]III\n%c[0,93,0,116] - %c[0,140,140,140] Brazos: %c[0,170,170,IIIA\n%c[0,93,0,116] - %c[0,140,140,140] Caderas: %c[0,170,170,170]III\n%c[0,93,0,116] - %c[0,140,140] Rodillas y espinillas: %c[0,170,170,IV\n%c[0,93,0,116] - %c[0,140,140] Pies: %c[0,170,170,IV</text>
	</string>
	
	<string id="st_helm_cloth_mask">
		<text>Mascara de tejido</text>
	</string>
	<string id="st_helm_cloth_mask_descr">
		<text>Un simple trozo de tela enrollado en forma de mascara. Suele ser utilizado por los acosadores para evitar la ingestion de particulas peligrosas, como medida de precaucion. Se recomienda llevarlo incluso en ausencia de una alarma de contador Geiger, ya que el aire puede estar contaminado en cierta medida. Sin embargo, puede acumular toxinas si se utiliza durante largos periodos de tiempo, por lo que es aconsejable tener siempre un repuesto para su rapida sustitucion. \n \n%c[0,170,170,170]CARACTERISTICAS:\n%c[0,153,255,255] - %c[0,140,140,140] mascara de trapo\n%c[255,238,153,26] - %c[0,140,140,140] utilizada cuando: %c[0,170,170,170] reparacion de equipos, mantenimiento de armas (+4%)\n \n%c[0,170,170,170]COMPONENTES:\n%c[0,93,0,116] - %c[0,140,140,140,140] tejido denso de una sola capa %c[0,170,170,170]224 g\n \n%c[0,170,170,170]CLASE DE BROMETERIA: \N - %c[0,93,0,116] - %c[0,140,140,140] Cabeza: %c[0,170,170,170]absent\n%c[0,93,0,116] - %c[0,140,140] Ojos: %c[0,170,170,170]ausente\n%c[0,93,0,116] - %c[0,140,140,140] Barbilla: %c[0,170,170,170]ausente\n%c[0,93,0,116] - %c[0,140,140,140] Cuello: %c[0,170,170,170]ausente</text>
	</string>
	
	<string id="st_helm_cloth_camo_mask">
		<text>Brazalete de camuflaje</text>
	</string>
	<string id="st_helm_cloth_camo_mask_descr">
		<text>Un simple trozo de tela de camuflaje enrollado en una mascara. Suele ser utilizado por los acosadores para evitar la ingestion de particulas peligrosas, como medida de precaucion. Se recomienda llevarlo incluso en ausencia de una alarma de contador Geiger, ya que el aire puede estar contaminado en cierta medida. Sin embargo, puede acumular toxinas si se utiliza durante largos periodos de tiempo, por lo que es aconsejable tener siempre un repuesto para su rapida sustitucion. \n \n%c[0,170,170,170]CARACTERISTICAS:\n%c[0,153,255,255] - %c[0,140,140,140] mascara de trapo\n%c[255,238,153,26] - %c[0,140,140,140] utilizada cuando: %c[0,170,170,170] reparacion de equipos, mantenimiento de armas (+4%)\n \n%c[0,170,170,170]COMPONENTES:\n%c[0,93,0,116] - %c[0,140,140,140,140] tejido denso de una sola capa %c[0,170,170,170]224 g\n \n%c[0,170,170,170]CLASE DE BROMETERIA: \N - %c[0,93,0,116] - %c[0,140,140,140] Cabeza: %c[0,170,170,170]absent\n%c[0,93,0,116] - %c[0,140,140] Ojos: %c[0,170,170,170]ausente\n%c[0,93,0,116] - %c[0,140,140,140] Barbilla: %c[0,170,170,170]ausente\n%c[0,93,0,116] - %c[0,140,140,140] Cuello: %c[0,170,170,170]ausente</text>
	</string>
	
	<string id="st_rp_bala_camo">
		<text>Pasamontanas de camuflaje</text>
	</string>
	<string id="st_rp_bala_camo_descr">
		<text>Pasamontanas de tela de camuflaje. No es peor que la venda de gasa de un acosador. \n \n%c[0,170,170,170]CARACTERISTICAS:\n%c[0,153,255,255] - %c[0,140,140,140] mascara de trapo\n%c[255,238,153,26] - %c[0,140,140,140] utilizada en: %c[0,170,170,170] reparacion de equipos, mantenimiento de armas (+4%)\n \n%c[0,170,170,170]COMPONENTES:\n%c[0,93,0,116] - %c[0,140,140,140,140] tejido denso de una sola capa %c[0,170,170,170]224 g\n \n%c[0,170,170,170]CLASE DE BROMETERIA: \N - %c[0,93,0,116] - %c[0,140,140,140] Cabeza: %c[0,170,170,170]absent\n%c[0,93,0,116] - %c[0,140,140] Ojos: %c[0,170,170,170]ausente\n%c[0,93,0,116] - %c[0,140,140,140] Barbilla: %c[0,170,170,170]ausente\n%c[0,93,0,116] - %c[0,140,140,140] Cuello: %c[0,170,170,170]ausente</text>
	</string>
	
	<string id="st_helm_respirator_freedom_camo">
		<text>Mascara de gas EO-20 PBF en camuflaje</text>
	</string>
	<string id="st_helm_respirator_freedom_camo_descr">
		<text>Mascara antigas estandar disenada para filtrar el polvo radiactivo y las toxinas del aire. Muy utilizado por los novatos y veteranos de Libertad por su funcionalidad. No tiene ninguna proteccion contra balas, fragmentos o efectos mecanicos. Pintado de camuflaje. \N - %c[0,170,170,170]CARACTERISTICAS:\N - %c[0,153,255,255] - %c[0,140,140,140] mascara de gas ligera \N - \N - [0,170,170,170]COMPONENTES: \n%c[0,93,0,116] - %c[0,140,140,140] mascara de gas PBF %c[0,170,170,170]760 g\n%c[0,93,0,116] - %c[0,140,140,140] filtro de respiracion EO-19 2x %c[0,170,170,170]210 g\n \n%c[0,170,170,170]CLASE DE QUEMADOR: \N - %c[0,93,0,116] - %c[0,140,140] Cabeza: %c[0,170,170]absent\n%c[0,93,0,116] - %c[0,140,140] Ojos: %c[0,170,170,170]I\n%c[0,93,0,116] - %c[0,140,140,140] Menton: %c[0,170,170,170]falta\n%c[0,93,0,116] - %c[0,140,140,140] Cuello: %c[0,170,170,170]falta</text>
	</string>
	
	<string id="st_helm_respirator_2_camo">
		<text>Mascara de gas EO-19 PBF en camuflaje</text>
	</string>
	<string id="st_helm_respirator_2_camo_descr">
		<text>Mascara antigas de goma, utilizada para filtrar el aire de particulas radiactivas y sustancias venenosas. Este antiguo modelo sigue siendo muy utilizado por los reclutas y veteranos de todas las facciones debido a su versatilidad, funcionalidad y bajo coste. No esta equipado con proteccion contra balas, fragmentos e impactos mecanicos. Esta pintado de camuflaje. \N - %c[0,170,170,170]CARACTERISTICAS:\N - %c[0,153,255,255] - %c[0,140,140,140] mascara de gas ligera \N - \N - [0,170,170,170]COMPONENTES: \n%c[0,93,0,116] - %c[0,140,140,140] mascara de gas PBF %c[0,170,170,170]760 g\n%c[0,93,0,116] - %c[0,140,140,140] filtro de respiracion EO-19 2x %c[0,170,170,170]210 g\n \n%c[0,170,170,170]CLASE DE QUEMADOR: \N - %c[0,93,0,116] - %c[0,140,140,140] Cabeza: %c[0,170,170,170]absent\n%c[0,93,0,116] - %c[0,140,140] Ojos: %c[0,170,170,170]I\n%c[0,93,0,116] - %c[0,140,140,140] Menton: %c[0,170,170,170]falta\n%c[0,93,0,116] - %c[0,140,140,140] Cuello: %c[0,170,170,170]falta</text>
	</string>
	
	<string id="cloak_outfit_name">
		<text>Chaqueta del cuerpo</text>
	</string>
	<string id="cloak_outfit_description">
		<text>Vieja chaqueta de hombre sovietica acolchada de color azul marino. Barata y extremadamente facil de producir, la chaqueta de algodon, la prenda exterior de invierno mas producida en masa en la URSS, ha sido siempre un simbolo de la ropa funcional, donde la estetica ha cedido completamente a consideraciones puramente pragmaticas. Inicialmente, hay dos soportes para modulos adicionales. \N - %c[0,170,170,170]CARACTERISTICAS:\N - %c[0,153,255,255] - %c[0,140,140,140] traje ligero\N - \N - [0,170,170,170]CLASE DE BRONCE: \N - %c[0,93,0,116] - %c[0,140,140,140] Torso: %c[0,170,170,170]\N - %c[0,140,140,140] Hombros: %c[0,170,170,170]\N - %c[0,93,0,116] - %c[0,140,140,140] Muneca: %c[0,170,170,170]absent\n%c[0,93,0,116] - %c[0,140,140,140] Brazos: %c[0,170,170,170]absent\n%c[0,93,0,116] - %c[0,140,140] Pies: %c[0,170,170,170]I\n%c[0,93,0,116] - %c[0,140,140] Rodillas y espinillas: %c[0,170,170,170]I\n%c[0,93,0,116] - %c[0,140,140] Pies: %c[0,170,170,170]ninguno</text>
	</string>
	
	<string id="trenchcoat_novice_name">
		<text>Una vieja capa de acampada</text>
	</string>
	<string id="trenchcoat_novice_description">
		<text>Capa larga de senderismo marron. Parece viejo y deteriorado, muchos parches y costuras que indican numerosas reparaciones. Es mejor utilizarlo con una mascara de gas o un sistema de respiracion cerrado. Inicialmente se instala un accesorio para modulos adicionales. \N - %c[0,170,170,170]CARACTERISTICAS:\N - %c[0,153,255,255] - %c[0,140,140,140] traje ligero\n \N - [0,170,170,170]CLASE DE BRONCEO: \N - %c[0,93,0,116] - %c[0,140,140,140] Torso: %c[0,170,170,170]\N - %c[0,140,140,140] Hombros: %c[0,170,170,170]\N - %c[0,93,0,116] - %c[0,140,140,140] Muneca: %c[0,170,170,170]absent\n%c[0,93,0,116] - %c[0,140,140,140] Brazos: %c[0,170,170,170]absent\n%c[0,93,0,116] - %c[0,140,140] Pies: %c[0,170,170,170]I\n%c[0,93,0,116] - %c[0,140,140] Rodillas y espinillas: %c[0,170,170,I\n%c[0,93,0,116] - %c[0,140,140] Pies: %c[0,170,170,I</text>
	</string>
	
	<string id="st_heavy_stalker_outfit_name">
		<text>El traje "Master"</text>
	</string>
	<string id="st_heavy_stalker_outfit_description">
		<text>El traje de acosador fabricado por los artesanos populares es una combinacion de un tejido engomado de dos capas con un forro de plexiglas y un chaleco blindado incorporado. Aunque el chaleco antibalas atraviesa incluso una bala de pistola, el traje es muy popular debido a su baratura y a su amplio margen de mejora. Equipado con tres contenedores de artefactos incorporados. \N - %c[0,170,170,170]CARACTERISTICAS:\N - %c[0,153,255,255] - %c[0,140,140,140] proteccion de armadura ligera\n \N - [0,170,170,170]Clase de proteccion de armadura: \N - %c[0,93,0,116] - %c[0,140,140,140] Torso: %c[0,170,170]IIIA\n%c[0,93,0,116] - %c[0,140,140,140] Hombros: %c[0,170,170]IIIA\n%c[0,93,0,116] - %c[0,140,140] Muneca: %c[0,170,170,170]III\n%c[0,93,0,116] - %c[0,140,140,140] Brazos: %c[0,170,170,170]none\n%c[0,93,0,116] - %c[0,140,140,140] Caderas: %c[0,170,170,170]III\n%c[0,93,0,116] - %c[0,140,140,140] Rodillas y espinillas: %c[0,170,170,II\n%c[0,93,0,116] - %c[0,140,140,140] Pies: %c[0,170,170,170]IIIA</text>
	</string>
	
	<string id="specops_outfit_2_name">
		<text>Beryl-6M</text>
	</string>
	<string id="specops_outfit_2_description">
		<text>La sexta generacion del traje de proteccion militar Beryl modificado en camuflaje urbano. Disenado para operaciones de asalto en zonas con alto fondo de radiacion, pero es ineficaz en condiciones de alta actividad anomala. Utilizado por los Stalkers a traves de los militares que cambian su equipo militar por bienes barbaros. Estan equipados con soportes para modulos adicionales. \N - %c[0,140,140,140] proteccion de armadura mejorada \N - %c[0,170,170,170]CLASE DE PROTECCION DE ARMADURA:\N - %c[0,93,0,116] - %c[0,140,140,140] Thors: %c[0,170,170,170]III\n%c[0,93,0,116] - %c[0,140,140,140] Hombros: %c[0,170,170,170]III\n%c[0,93,0,116] - %c[0,140,140,140] Muneca: %c[0,170,170,170]IIIA\n%c[0,93,0,116] - %c[0,140,140] Brazos: %c[0,170,170,170]II\n%c[0,93,0,116] - %c[0,140,140,140] Caderas: %c[0,170,170,170]IIIA\n%c[0,93,0,116] - %c[0,140,140] Rodillas y espinillas: %c[0,170,170,170]III\n%c[0,93,0,116] - %c[0,140,140,140] Pies: %c[0,170,170,170]III\n%c[0,170,170,170]PIES:\n%c[0,100,0,15] - %c[0,140,140,140] aumento de la proteccion anormal</text>
	</string>
	
	<string id="exo_specops_name">
		<text>Beryl-5M con servomotores</text>
	</string>
	<string id="exo_specops_description">
		<text>Un Beryl-5M del ejercito regular que ha sido equipado de fabrica con servos fuera del perimetro. A diferencia del exoesqueleto, permite correr y no lleva casco incorporado. Contiene un contenedor integrado para la fijacion del modulo. \N - %c[0,170,170,170]CARACTERISTICAS:\N-[0,153,255,255] - %c[0,140,140,140] exoesqueleto\n \N-[0,170,170,170]CLASE DE CEREBRO:\N-[0,93,0,116] - %c[0,140,140,140,140] Thors: %c[0,170,170,170]III\n%c[0,93,0,116] - %c[0,140,140,140] Hombros: %c[0,170,170,170]III\n%c[0,93,0,116] - %c[0,140,140,140] Muneca: %c[0,170,170,170]IIIA\n%c[0,93,0,116] - %c[0,140,140] Brazos: %c[0,170,170,170]II\n%c[0,93,0,116] - %c[0,140,140,140] Caderas: %c[0,170,170,170]II\n%c[0,93,0,116] - %c[0,140,140,140] Rodillas y espinillas: %c[0,170,170,170]III\n%c[0,93,0,116] - %c[0,140,140,140] Pies: %c[0,170,170,170]III\n \n%c[0,170,170]FEet:\n%c[0,100,0,15] - %c[0,140,140,140,140] aumento del parametro "Shock Shielding"</text>
	</string>
</string_table>			 